src/__init__.py
src/config.py
src/logging.py
src/main.py
src/crawler/__init__.py
src/crawler/cache.py
src/crawler/checkpoint.py
src/crawler/fetcher.py
src/crawler/parser.py
src/crawler/pipeline.py
src/crawler/scheduler.py
src/models/__init__.py
src/models/schemas.py
src/presets/__init__.py
src/presets/registry.py
src/presets/schemas/amazon_products.yaml
src/presets/schemas/bbc_news.yaml
src/presets/schemas/ebay_listings.yaml
src/presets/schemas/github_repos.yaml
src/presets/schemas/hacker_news.yaml
src/presets/schemas/quotes_toscrape.yaml
src/presets/schemas/reddit.yaml
src/presets/schemas/wikipedia_articles.yaml
src/schema/__init__.py
src/schema/base.py
src/schema/coercion.py
src/schema/extractor.py
src/schema/parquet_mapper.py
src/schema/yaml_loader.py
ergane-0.4.0.dist-info/METADATA
ergane-0.4.0.dist-info/WHEEL
ergane-0.4.0.dist-info/entry_points.txt
ergane-0.4.0.dist-info/licenses/LICENSE
ergane-0.4.0.dist-info/RECORD
