Metadata-Version: 2.4
Name: ergane
Version: 0.4.0
Summary: High-performance async web scraper with selectolax parsing
Project-URL: Homepage, https://github.com/pyamin1878/ergane
Project-URL: Repository, https://github.com/pyamin1878/ergane
Project-URL: Issues, https://github.com/pyamin1878/ergane/issues
Author: pyamin1878
License: MIT
License-File: LICENSE
Keywords: async,crawler,httpx,selectolax,spider,web-scraper
Classifier: Development Status :: 4 - Beta
Classifier: Framework :: AsyncIO
Classifier: Intended Audience :: Developers
Classifier: License :: OSI Approved :: MIT License
Classifier: Programming Language :: Python :: 3
Classifier: Programming Language :: Python :: 3.10
Classifier: Programming Language :: Python :: 3.11
Classifier: Programming Language :: Python :: 3.12
Classifier: Topic :: Internet :: WWW/HTTP
Requires-Python: >=3.10
Requires-Dist: click>=8.1.0
Requires-Dist: fastexcel>=0.7.0
Requires-Dist: httpx[http2]>=0.27.0
Requires-Dist: polars>=1.0.0
Requires-Dist: pydantic>=2.0.0
Requires-Dist: pyyaml>=6.0.0
Requires-Dist: rich>=13.0.0
Requires-Dist: selectolax>=0.3.21
Requires-Dist: xlsxwriter>=3.1.0
Provides-Extra: dev
Requires-Dist: beautifulsoup4>=4.12.0; extra == 'dev'
Requires-Dist: lxml>=5.0.0; extra == 'dev'
Requires-Dist: mypy>=1.8.0; extra == 'dev'
Requires-Dist: pytest-asyncio>=0.23.0; extra == 'dev'
Requires-Dist: pytest-cov>=4.1.0; extra == 'dev'
Requires-Dist: pytest>=8.0.0; extra == 'dev'
Requires-Dist: ruff>=0.2.0; extra == 'dev'
